.gitignore
README.rst
setup.py
django_centralniak_slugfield/__init__.py
django_centralniak_slugfield/fields.py
django_centralniak_slugfield/slughifi.py
django_centralniak_slugfield.egg-info/PKG-INFO
django_centralniak_slugfield.egg-info/SOURCES.txt
django_centralniak_slugfield.egg-info/dependency_links.txt
django_centralniak_slugfield.egg-info/top_level.txt