Metadata-Version: 1.1
Name: django-centralniak-slugfield
Version: 0.1.2
Summary: Provides more handy support for slugs in models
Home-page: http://github.com/centralniak
Author: Piotr Kilczuk
Author-email: p.kilczuk@neumea.pl
License: UNKNOWN
Platform: UNKNOWN
Classifier: Framework :: Django
Classifier: Environment :: Web Environment
Classifier: Programming Language :: Python
Classifier: Intended Audience :: Developers
Classifier: Operating System :: OS Independent
Classifier: License :: OSI Approved :: BSD License
Classifier: Topic :: Software Development :: Libraries :: Python Modules
Provides: django_centralniak_slugfield
